{
 "attached_to_doctype": "Print Format",
 "attached_to_field": "print_designer_preview_img",
 "attached_to_name": "Sales Invoice PD Format v2",
 "content_hash": "360404e78fedf97c58269738b5e58b64",
 "creation": "2024-04-16 19:22:32.564571",
 "docstatus": 0,
 "doctype": "File",
 "file_name": "print_designer-sales_invoice_pd_format_v2-preview.jpg",
 "file_size": 148126,
 "file_type": "JPG",
 "file_url": "/private/files/print_designer-sales_invoice_pd_format_v2-preview.jpg",
 "folder": "Home",
 "idx": 0,
 "is_attachments_folder": 0,
 "is_folder": 0,
 "is_home_folder": 0,
 "is_private": 1,
 "modified": "2024-04-16 19:22:32.564571",
 "modified_by": "Administrator",
 "name": "040d5e33f6",
 "owner": "Administrator",
 "uploaded_to_dropbox": 0,
 "uploaded_to_google_drive": 0
}